<?xml version="1.0" encoding="UTF-8"?>
<con:soapui-project id="bca27217-6d47-47b8-aff1-14905a2496a6" activeEnvironment="Default" name="Customers2Controller" soapui-version="5.2.1" xmlns:con="http://eviware.com/soapui/config"><con:settings/><con:interface xsi:type="con:RestService" id="e6596a11-50eb-4ebd-9b4e-5af6bc870729" wadlVersion="http://wadl.dev.java.net/2009/02" name="http://localhost:60571" type="rest" xmlns:xsi="http://www.w3.org/2001/XMLSchema-instance"><con:settings/><con:definitionCache/><con:endpoints><con:endpoint>http://localhost:60571</con:endpoint></con:endpoints><con:resource name="" path="/api/Customer2" id="39a4c86b-4a0c-4d2d-b89a-c9a3b9cb1883"><con:settings/><con:parameters/><con:method name="" id="ad008c1d-0979-49fd-9b56-d86cb1b4c370" method="GET"><con:settings/><con:parameters/><con:representation type="RESPONSE"><con:mediaType xsi:nil="true"/><con:status>0</con:status><con:params/><con:element>data</con:element></con:representation><con:representation type="RESPONSE"><con:mediaType xsi:nil="true"/><con:status>0</con:status><con:params/><con:element>data</con:element></con:representation><con:request name="Request 1" id="dd0bd983-b25c-4d5c-90bd-5dc5752fefe8" mediaType="application/json"><con:settings><con:setting id="com.eviware.soapui.impl.wsdl.WsdlRequest@request-headers">&lt;xml-fragment/></con:setting></con:settings><con:endpoint>http://localhost:60571</con:endpoint><con:request/><con:originalUri>http://localhost/api/Customers2</con:originalUri><con:credentials><con:authType>No Authorization</con:authType></con:credentials><con:jmsConfig JMSDeliveryMode="PERSISTENT"/><con:jmsPropertyConfig/><con:parameters/></con:request></con:method></con:resource></con:interface><con:properties/><con:wssContainer/><con:oAuth2ProfileContainer/><con:sensitiveInformation/></con:soapui-project>